.gitignore
LICENSE
README.md
requirements.txt
text2png/__init__.py
text2png/core.py
text2png/pkg_data.ttc
text2png-0.5.0.dist-info/LICENSE
text2png-0.5.0.dist-info/METADATA
text2png-0.5.0.dist-info/WHEEL
text2png-0.5.0.dist-info/top_level.txt
text2png-0.5.0.dist-info/RECORD
