Metadata-Version: 2.1
Name: text2png
Version: 0.5.0
Summary: Easiest way to create text thumbnail.
Home-page: https://github.com/foxe6/text2png
Author: f̣ộx̣ệ6
Author-email: foxe6@protonmail.com
License: AGPL-3.0
Keywords: convert text to image png
Platform: UNKNOWN
Classifier: Programming Language :: Python :: 3.9
Classifier: Topic :: Utilities
Classifier: Natural Language :: English
Classifier: Intended Audience :: Developers
Classifier: License :: OSI Approved :: GNU Affero General Public License v3
Classifier: Operating System :: Microsoft :: Windows :: Windows 10
Requires-Python: >=3
License-File: LICENSE
Requires-Dist: pillow (>=0.0.1)
Requires-Dist: omnitools (>=0.0.1)
